[{"coordinates":{"world_space":[-4.75,155.75,-142.84518828451885]},"type":{"spine_segment":"T","spine_segment_probabilities":[0.022376859560608864,0.9943888783454895,0.03548819571733475],"keypoint_type":"body"}},{"coordinates":{"world_space":[-3.25,146.75,-171.33723849372387]},"type":{"spine_segment":"L","spine_segment_probabilities":[0.03148115053772926,0.040375079959630966,0.9936466217041016],"keypoint_type":"body"}},{"coordinates":{"world_space":[-0.25,139.25,-204.32803347280338]},"type":{"spine_segment":"L","spine_segment_probabilities":[0.02784310095012188,0.022144190967082977,0.9947052597999573],"keypoint_type":"body"}},{"coordinates":{"world_space":[2.75,134.75,-313.79748953974894]},"type":{"spine_segment":"L","spine_segment_probabilities":[0.021060027182102203,0.015635130926966667,0.9954577088356018],"keypoint_type":"body"}},{"coordinates":{"world_space":[2.75,130.25,-277.8075313807532]},"type":{"spine_segment":"L","spine_segment_probabilities":[0.02648232877254486,0.017910152673721313,0.9951044321060181],"keypoint_type":"body"}},{"coordinates":{"world_space":[2.75,131.75,-240.3179916317992]},"type":{"spine_segment":"L","spine_segment_probabilities":[0.025818178430199623,0.01916355825960636,0.995150089263916],"keypoint_type":"body"}},{"coordinates":{"world_space":[20.75,151.25,-270.30962343096235]},"type":{"spine_segment_probabilities":[0.0,0.0,0.0],"keypoint_type":"left"}},{"coordinates":{"world_space":[8.75,176.75,-139.84602510460255]},"type":{"spine_segment_probabilities":[0.0,0.0,0.0],"keypoint_type":"left"}},{"coordinates":{"world_space":[25.25,152.75,-303.30041841004186]},"type":{"spine_segment_probabilities":[0.0,0.0,0.0],"keypoint_type":"left"}},{"coordinates":{"world_space":[13.25,170.75,-169.83765690376572]},"type":{"spine_segment_probabilities":[0.0,0.0,0.0],"keypoint_type":"left"}},{"coordinates":{"world_space":[14.75,161.75,-199.8292887029289]},"type":{"spine_segment_probabilities":[0.0,0.0,0.0],"keypoint_type":"left"}},{"coordinates":{"world_space":[17.75,152.75,-235.8192468619247]},"type":{"spine_segment_probabilities":[0.0,0.0,0.0],"keypoint_type":"left"}},{"coordinates":{"world_space":[-12.25,151.25,-271.8092050209205]},"type":{"spine_segment_probabilities":[0.0,0.0,0.0],"keypoint_type":"right"}},{"coordinates":{"world_space":[-16.75,169.25,-171.33723849372387]},"type":{"spine_segment_probabilities":[0.0,0.0,0.0],"keypoint_type":"right"}},{"coordinates":{"world_space":[-12.25,152.75,-237.31882845188287]},"type":{"spine_segment_probabilities":[0.0,0.0,0.0],"keypoint_type":"right"}},{"coordinates":{"world_space":[-18.25,176.75,-139.84602510460255]},"type":{"spine_segment_probabilities":[0.0,0.0,0.0],"keypoint_type":"right"}},{"coordinates":{"world_space":[-16.75,152.75,-303.30041841004186]},"type":{"spine_segment_probabilities":[0.0,0.0,0.0],"keypoint_type":"right"}},{"coordinates":{"world_space":[-15.25,161.75,-204.32803347280338]},"type":{"spine_segment_probabilities":[0.0,0.0,0.0],"keypoint_type":"right"}}]