[{"coordinates":{"world_space":[-7.476199922107515,-17.942879813058035,-59.25]},"type":{"spine_segment":"T","spine_segment_probabilities":[0.03787865862250328,0.9921594858169556,0.019750721752643585],"keypoint_type":"body"}},{"coordinates":{"world_space":[-11.961919875372024,-13.457159859793526,-80.25]},"type":{"spine_segment":"T","spine_segment_probabilities":[0.039614904671907425,0.9913344979286194,0.017233772203326225],"keypoint_type":"body"}},{"coordinates":{"world_space":[-2.990479968843006,-29.90479968843006,-17.25]},"type":{"spine_segment":"T","spine_segment_probabilities":[0.2485232800245285,0.979928195476532,0.03752407431602478],"keypoint_type":"body"}},{"coordinates":{"world_space":[-16.447639828636532,-8.971439906529017,-101.25]},"type":{"spine_segment":"T","spine_segment_probabilities":[0.02890964224934578,0.988682746887207,0.02119177207350731],"keypoint_type":"body"}},{"coordinates":{"world_space":[-4.485719953264509,-23.923839750744047,-38.25]},"type":{"spine_segment":"T","spine_segment_probabilities":[0.04675987735390663,0.9866884350776672,0.019927890971302986],"keypoint_type":"body"}},{"coordinates":{"world_space":[-1.495239984421503,-37.38099961053757,2.25]},"type":{"spine_segment":"C","spine_segment_probabilities":[0.9864441156387329,0.024063752964138985,0.020134612917900085],"keypoint_type":"body"}},{"coordinates":{"world_space":[-4.485719953264509,-43.36195954822359,75.75]},"type":{"spine_segment":"C","spine_segment_probabilities":[0.9831027984619141,0.016700051724910736,0.023340614512562752],"keypoint_type":"body"}},{"coordinates":{"world_space":[-20.933359781901043,-5.980959937686012,-122.25]},"type":{"spine_segment":"T","spine_segment_probabilities":[0.038761600852012634,0.9902282357215881,0.028854941949248314],"keypoint_type":"body"}},{"coordinates":{"world_space":[-4.485719953264509,-44.85719953264509,57.75]},"type":{"spine_segment":"C","spine_segment_probabilities":[0.9869604706764221,0.01944764517247677,0.024451090022921562],"keypoint_type":"body"}},{"coordinates":{"world_space":[-2.990479968843006,-43.36195954822359,39.75]},"type":{"spine_segment":"C","spine_segment_probabilities":[0.9853245615959167,0.023960266262292862,0.021566201001405716],"keypoint_type":"body"}},{"coordinates":{"world_space":[-1.495239984421503,-43.36195954822359,21.75]},"type":{"spine_segment":"C","spine_segment_probabilities":[0.9786162376403809,0.02467362955212593,0.025046488270163536],"keypoint_type":"body"}},{"coordinates":{"world_space":[-4.485719953264509,-40.37147957938058,98.25]},"type":{"spine_segment":"C","spine_segment_probabilities":[0.9767699241638184,0.018964271992444992,0.04048885405063629],"keypoint_type":"body"}},{"coordinates":{"world_space":[-5.980959937686012,-40.37147957938058,114.75]},"type":{"spine_segment":"C","spine_segment_probabilities":[0.9740167856216431,0.015626292675733566,0.018530013039708138],"keypoint_type":"body"}},{"coordinates":{"world_space":[2.990479968843006,-4.485719953264509,-50.25]},"type":{"spine_segment_probabilities":[0.0,0.0,0.0],"keypoint_type":"left"}},{"coordinates":{"world_space":[4.485719953264509,-10.466679890950521,-27.75]},"type":{"spine_segment_probabilities":[0.0,0.0,0.0],"keypoint_type":"left"}},{"coordinates":{"world_space":[-1.495239984421503,1.495239984421503,-69.75]},"type":{"spine_segment_probabilities":[0.0,0.0,0.0],"keypoint_type":"left"}},{"coordinates":{"world_space":[-5.980959937686012,4.485719953264509,-92.25]},"type":{"spine_segment_probabilities":[0.0,0.0,0.0],"keypoint_type":"left"}},{"coordinates":{"world_space":[8.971439906529017,-19.438119797479537,-8.25]},"type":{"spine_segment_probabilities":[0.0,0.0,0.0],"keypoint_type":"left"}},{"coordinates":{"world_space":[-8.971439906529017,13.457159859793526,-113.25]},"type":{"spine_segment_probabilities":[0.0,0.0,0.0],"keypoint_type":"left"}},{"coordinates":{"world_space":[-8.971439906529017,18.69047955763522,-136.5000203120908]},"type":{"spine_segment_probabilities":[0.0,0.0,0.0],"keypoint_type":"left"}},{"coordinates":{"world_space":[8.971439906529017,-25.41907973516555,90.75]},"type":{"spine_segment_probabilities":[0.0,0.0,0.0],"keypoint_type":"left"}},{"coordinates":{"world_space":[11.961919875372024,-19.438119797479537,105.75]},"type":{"spine_segment_probabilities":[0.0,0.0,0.0],"keypoint_type":"left"}},{"coordinates":{"world_space":[10.466679890950521,-26.914319719587052,9.75]},"type":{"spine_segment_probabilities":[0.0,0.0,0.0],"keypoint_type":"left"}},{"coordinates":{"world_space":[10.466679890950521,-31.400039672851562,77.25]},"type":{"spine_segment_probabilities":[0.0,0.0,0.0],"keypoint_type":"left"}},{"coordinates":{"world_space":[10.466679890950521,-31.400039672851562,60.75]},"type":{"spine_segment_probabilities":[0.0,0.0,0.0],"keypoint_type":"left"}},{"coordinates":{"world_space":[10.466679890950521,-28.409559704008558,27.75]},"type":{"spine_segment_probabilities":[0.0,0.0,0.0],"keypoint_type":"left"}},{"coordinates":{"world_space":[8.971439906529017,-28.409559704008558,44.25]},"type":{"spine_segment_probabilities":[0.0,0.0,0.0],"keypoint_type":"left"}},{"coordinates":{"world_space":[-1.495239984421503,-13.457159859793526,8.25]},"type":{"spine_segment_probabilities":[0.0,0.0,0.0],"keypoint_type":"left"}},{"coordinates":{"world_space":[-26.914319719587052,2.990479968843006,-92.25]},"type":{"spine_segment_probabilities":[0.0,0.0,0.0],"keypoint_type":"right"}},{"coordinates":{"world_space":[-22.428599766322545,-2.990479968843006,-69.75]},"type":{"spine_segment_probabilities":[0.0,0.0,0.0],"keypoint_type":"right"}},{"coordinates":{"world_space":[-17.942879813058035,-17.942879813058035,-29.25]},"type":{"spine_segment_probabilities":[0.0,0.0,0.0],"keypoint_type":"right"}},{"coordinates":{"world_space":[-19.438119797479537,-25.41907973516555,-8.25]},"type":{"spine_segment_probabilities":[0.0,0.0,0.0],"keypoint_type":"right"}},{"coordinates":{"world_space":[-31.400039672851562,10.466679890950521,-113.25]},"type":{"spine_segment_probabilities":[0.0,0.0,0.0],"keypoint_type":"right"}},{"coordinates":{"world_space":[-19.438119797479537,-10.466679890950521,-48.75]},"type":{"spine_segment_probabilities":[0.0,0.0,0.0],"keypoint_type":"right"}},{"coordinates":{"world_space":[-31.400039672851562,14.95239984421503,-137.25]},"type":{"spine_segment_probabilities":[0.0,0.0,0.0],"keypoint_type":"right"}},{"coordinates":{"world_space":[-22.428599766322545,-31.400039672851562,90.75]},"type":{"spine_segment_probabilities":[0.0,0.0,0.0],"keypoint_type":"right"}},{"coordinates":{"world_space":[-19.438119797479537,-32.895279657273065,9.75]},"type":{"spine_segment_probabilities":[0.0,0.0,0.0],"keypoint_type":"right"}},{"coordinates":{"world_space":[-19.438119797479537,-37.38099961053757,27.75]},"type":{"spine_segment_probabilities":[0.0,0.0,0.0],"keypoint_type":"right"}},{"coordinates":{"world_space":[-19.438119797479537,-38.876239594959074,42.75]},"type":{"spine_segment_probabilities":[0.0,0.0,0.0],"keypoint_type":"right"}},{"coordinates":{"world_space":[-23.923839750744047,-20.933359781901043,105.75]},"type":{"spine_segment_probabilities":[0.0,0.0,0.0],"keypoint_type":"right"}},{"coordinates":{"world_space":[-20.933359781901043,-37.38099961053757,60.75]},"type":{"spine_segment_probabilities":[0.0,0.0,0.0],"keypoint_type":"right"}},{"coordinates":{"world_space":[-20.933359781901043,-32.895279657273065,75.75]},"type":{"spine_segment_probabilities":[0.0,0.0,0.0],"keypoint_type":"right"}}]