[{"coordinates":{"world_space":[-0.881908574380165,278.1484375,-72.14435261708]},"type":{"spine_level":"T6","keypoint_type":"body"}},{"coordinates":{"world_space":[-0.881908574380165,272.898723821343,-93.9146116531354]},"type":{"spine_level":"T7","keypoint_type":"body"}},{"coordinates":{"world_space":[-2.37777634297521,266.1484375,-117.18567493113]},"type":{"spine_level":"T8","keypoint_type":"body"}},{"coordinates":{"world_space":[-0.881908574380165,260.1484375,-139.706336088154]},"type":{"spine_level":"T9","keypoint_type":"body"}},{"coordinates":{"world_space":[2.10982696280992,252.6484375,-165.229752066116]},"type":{"spine_level":"T10","keypoint_type":"body"}},{"coordinates":{"world_space":[2.10982696280992,242.1484375,-192.254545454546]},"type":{"spine_level":"T11","keypoint_type":"body"}},{"coordinates":{"world_space":[3.60569473140496,233.1484375,-220.780716253444]},"type":{"spine_level":"T12","keypoint_type":"body"}},{"coordinates":{"world_space":[3.60569473140496,221.1484375,-253.811019283747]},"type":{"spine_level":"L1","keypoint_type":"body"}},{"coordinates":{"world_space":[6.59743026859504,207.6484375,-288.342699724518]},"type":{"spine_level":"L2","keypoint_type":"body"}},{"coordinates":{"world_space":[6.59743026859504,197.1484375,-325.877134986226]},"type":{"spine_level":"L3","keypoint_type":"body"}},{"coordinates":{"world_space":[6.59743026859504,194.1484375,-361.910192837466]},"type":{"spine_level":"L4","keypoint_type":"body"}},{"coordinates":{"world_space":[5.1015625,197.1484375,-394.940495867769]},"type":{"spine_level":"L5","keypoint_type":"body"}},{"coordinates":{"world_space":[11.0850335743802,299.1484375,-64.6374655647384]},"type":{"keypoint_type":"left"}},{"coordinates":{"world_space":[12.5809013429752,299.1484375,-90.1608815426998]},"type":{"keypoint_type":"left"}},{"coordinates":{"world_space":[12.5809013429752,293.1484375,-115.684297520661]},"type":{"keypoint_type":"left"}},{"coordinates":{"world_space":[14.0767691115702,287.1484375,-141.207713498623]},"type":{"keypoint_type":"left"}},{"coordinates":{"world_space":[17.0685046487603,278.1484375,-166.731129476584]},"type":{"keypoint_type":"left"}},{"coordinates":{"world_space":[20.0602401859504,269.1484375,-195.257300275482]},"type":{"keypoint_type":"left"}},{"coordinates":{"world_space":[21.5561079545455,258.6484375,-225.284848484849]},"type":{"keypoint_type":"left"}},{"coordinates":{"world_space":[21.5561079545455,246.6484375,-256.813774104683]},"type":{"keypoint_type":"left"}},{"coordinates":{"world_space":[23.0519757231405,234.6484375,-289.844077134986]},"type":{"keypoint_type":"left"}},{"coordinates":{"world_space":[26.0437112603306,224.1484375,-324.375757575758]},"type":{"keypoint_type":"left"}},{"coordinates":{"world_space":[29.0354467975207,218.1484375,-355.904683195592]},"type":{"keypoint_type":"left"}},{"coordinates":{"world_space":[33.5230501033058,219.6484375,-384.43085399449]},"type":{"keypoint_type":"left"}},{"coordinates":{"world_space":[-9.85711518595041,299.1484375,-66.1388429752067]},"type":{"keypoint_type":"right"}},{"coordinates":{"world_space":[-9.85711518595041,299.1484375,-91.6622589531681]},"type":{"keypoint_type":"right"}},{"coordinates":{"world_space":[-9.85711518595041,293.1484375,-117.18567493113]},"type":{"keypoint_type":"right"}},{"coordinates":{"world_space":[-9.85711518595041,285.6484375,-141.207713498623]},"type":{"keypoint_type":"right"}},{"coordinates":{"world_space":[-9.85711518595041,278.1484375,-168.232506887052]},"type":{"keypoint_type":"right"}},{"coordinates":{"world_space":[-9.85711518595041,270.6484375,-196.75867768595]},"type":{"keypoint_type":"right"}},{"coordinates":{"world_space":[-9.85711518595041,261.6484375,-226.786225895317]},"type":{"keypoint_type":"right"}},{"coordinates":{"world_space":[-9.85711518595041,248.1484375,-258.315151515152]},"type":{"keypoint_type":"right"}},{"coordinates":{"world_space":[-9.85711518595041,236.1484375,-289.844077134986]},"type":{"keypoint_type":"right"}},{"coordinates":{"world_space":[-12.8488507231405,225.6484375,-324.375757575758]},"type":{"keypoint_type":"right"}},{"coordinates":{"world_space":[-15.8405862603306,219.6484375,-357.406060606061]},"type":{"keypoint_type":"right"}},{"coordinates":{"world_space":[-21.8240573347107,221.1484375,-382.929476584022]},"type":{"keypoint_type":"right"}}]