[{"coordinates":{"world_space":[15.832257231405,234.009607919255,-247.15]},"type":{"spine_level":"T10","keypoint_type":"body"}},{"coordinates":{"world_space":[14.328125,228.022030279503,-269.65]},"type":{"spine_level":"T11","keypoint_type":"body"}},{"coordinates":{"world_space":[12.823992768595,222.034452639752,-298.15]},"type":{"spine_level":"T12","keypoint_type":"body"}},{"coordinates":{"world_space":[12.823992768595,213.053086180124,-329.65]},"type":{"spine_level":"L1","keypoint_type":"body"}},{"coordinates":{"world_space":[12.823992768595,201.077930900621,-362.65]},"type":{"spine_level":"L2","keypoint_type":"body"}},{"coordinates":{"world_space":[11.3198605371901,187.60588121118,-395.65]},"type":{"spine_level":"L3","keypoint_type":"body"}},{"coordinates":{"world_space":[9.81572830578512,175.630725931677,-428.65]},"type":{"spine_level":"L4","keypoint_type":"body"}},{"coordinates":{"world_space":[6.80746384297521,171.140042701863,-466.15]},"type":{"spine_level":"L5","keypoint_type":"body"}},{"coordinates":{"world_space":[30.8735795454545,251.972340838509,-242.65]},"type":{"keypoint_type":"left"}},{"coordinates":{"world_space":[32.3777117768595,247.481657608696,-266.65]},"type":{"keypoint_type":"left"}},{"coordinates":{"world_space":[32.3777117768595,241.494079968944,-296.65]},"type":{"keypoint_type":"left"}},{"coordinates":{"world_space":[30.8735795454545,234.009607919255,-329.65]},"type":{"keypoint_type":"left"}},{"coordinates":{"world_space":[29.3694473140496,222.034452639752,-362.65]},"type":{"keypoint_type":"left"}},{"coordinates":{"world_space":[29.3694473140496,210.059297360248,-397.15]},"type":{"keypoint_type":"left"}},{"coordinates":{"world_space":[29.3694473140496,199.581036490683,-428.65]},"type":{"keypoint_type":"left"}},{"coordinates":{"world_space":[30.8735795454545,193.593458850932,-460.15]},"type":{"keypoint_type":"left"}},{"coordinates":{"world_space":[9.81572830578512,256.463024068323,-242.65]},"type":{"keypoint_type":"right"}},{"coordinates":{"world_space":[8.31159607438017,250.475446428571,-266.65]},"type":{"keypoint_type":"right"}},{"coordinates":{"world_space":[5.30333161157025,247.481657608696,-296.65]},"type":{"keypoint_type":"right"}},{"coordinates":{"world_space":[3.79919938016529,238.500291149068,-329.65]},"type":{"keypoint_type":"right"}},{"coordinates":{"world_space":[3.79919938016529,226.525135869565,-362.65]},"type":{"keypoint_type":"right"}},{"coordinates":{"world_space":[0.79093491735537,213.053086180124,-395.65]},"type":{"keypoint_type":"right"}},{"coordinates":{"world_space":[-3.72146177685951,201.077930900621,-427.15]},"type":{"keypoint_type":"right"}},{"coordinates":{"world_space":[-11.2421229338843,195.09035326087,-455.65]},"type":{"keypoint_type":"right"}}]