[{"coordinates":{"world_space":[35.0625,187.75,-40.2448275862069]},"type":{"spine_level":"T10","keypoint_type":"body"}},{"coordinates":{"world_space":[38.0625,183.25,-64.275478927203]},"type":{"spine_level":"T11","keypoint_type":"body"}},{"coordinates":{"world_space":[39.5625,180.25,-92.811877394636]},"type":{"spine_level":"T12","keypoint_type":"body"}},{"coordinates":{"world_space":[41.0625,177.25,-122.850191570881]},"type":{"spine_level":"L1","keypoint_type":"body"}},{"coordinates":{"world_space":[42.5625,172.75,-155.892337164751]},"type":{"spine_level":"L2","keypoint_type":"body"}},{"coordinates":{"world_space":[42.5625,169.75,-188.934482758621]},"type":{"spine_level":"L3","keypoint_type":"body"}},{"coordinates":{"world_space":[41.0625,169.75,-221.97662835249]},"type":{"spine_level":"L4","keypoint_type":"body"}},{"coordinates":{"world_space":[38.0625,175.75,-255.01877394636]},"type":{"spine_level":"L5","keypoint_type":"body"}},{"coordinates":{"world_space":[47.0625,207.25,-34.2371647509578]},"type":{"keypoint_type":"left"}},{"coordinates":{"world_space":[50.0625,202.75,-58.267816091954]},"type":{"keypoint_type":"left"}},{"coordinates":{"world_space":[53.0625,202.75,-86.8042145593869]},"type":{"keypoint_type":"left"}},{"coordinates":{"world_space":[53.0625,199.75,-116.842528735632]},"type":{"keypoint_type":"left"}},{"coordinates":{"world_space":[54.5625,198.25,-149.884674329502]},"type":{"keypoint_type":"left"}},{"coordinates":{"world_space":[56.0625,195.25,-182.926819923372]},"type":{"keypoint_type":"left"}},{"coordinates":{"world_space":[54.5625,192.25,-214.467049808429]},"type":{"keypoint_type":"left"}},{"coordinates":{"world_space":[59.0625,196.75,-247.509195402299]},"type":{"keypoint_type":"left"}},{"coordinates":{"world_space":[23.0625,204.25,-37.2409961685824]},"type":{"keypoint_type":"right"}},{"coordinates":{"world_space":[24.5625,199.75,-59.7697318007663]},"type":{"keypoint_type":"right"}},{"coordinates":{"world_space":[24.5625,196.75,-88.3061302681992]},"type":{"keypoint_type":"right"}},{"coordinates":{"world_space":[26.0625,195.25,-118.344444444444]},"type":{"keypoint_type":"right"}},{"coordinates":{"world_space":[26.0625,192.25,-149.884674329502]},"type":{"keypoint_type":"right"}},{"coordinates":{"world_space":[24.5625,189.25,-182.926819923372]},"type":{"keypoint_type":"right"}},{"coordinates":{"world_space":[23.0625,187.75,-212.965134099617]},"type":{"keypoint_type":"right"}},{"coordinates":{"world_space":[15.5625,186.25,-244.505363984674]},"type":{"keypoint_type":"right"}}]