[{"coordinates":{"world_space":[43.1318359375,-132.1142578125,-1.05153583617715]},"type":{"spine_level":"T9","keypoint_type":"body"}},{"coordinates":{"world_space":[40.1318359375,-132.1142578125,-25.0788395904434]},"type":{"spine_level":"T10","keypoint_type":"body"}},{"coordinates":{"world_space":[37.1318359375,-132.1142578125,-50.6078498293512]},"type":{"spine_level":"T11","keypoint_type":"body"}},{"coordinates":{"world_space":[35.6318359375,-132.1142578125,-79.1402730375423]},"type":{"spine_level":"T12","keypoint_type":"body"}},{"coordinates":{"world_space":[35.6318359375,-133.6142578125,-109.174402730375]},"type":{"spine_level":"L1","keypoint_type":"body"}},{"coordinates":{"world_space":[34.1318359375,-135.1142578125,-140.71023890785]},"type":{"spine_level":"L2","keypoint_type":"body"}},{"coordinates":{"world_space":[32.6318359375,-139.6142578125,-173.747781569966]},"type":{"spine_level":"L3","keypoint_type":"body"}},{"coordinates":{"world_space":[32.6318359375,-142.6142578125,-208.287030716723]},"type":{"spine_level":"L4","keypoint_type":"body"}},{"coordinates":{"world_space":[32.6318359375,-138.1142578125,-242.826279863481]},"type":{"spine_level":"L5","keypoint_type":"body"}},{"coordinates":{"world_space":[61.1318359375,-117.1142578125,4.9552901023894]},"type":{"keypoint_type":"left"}},{"coordinates":{"world_space":[59.6318359375,-117.1142578125,-19.0720136518768]},"type":{"keypoint_type":"left"}},{"coordinates":{"world_space":[56.6318359375,-117.1142578125,-46.1027303754263]},"type":{"keypoint_type":"left"}},{"coordinates":{"world_space":[56.6318359375,-117.1142578125,-76.1368600682591]},"type":{"keypoint_type":"left"}},{"coordinates":{"world_space":[55.1318359375,-115.6142578125,-106.170989761092]},"type":{"keypoint_type":"left"}},{"coordinates":{"world_space":[54.3825902517609,-116.365012126761,-136.955217523834]},"type":{"keypoint_type":"left"}},{"coordinates":{"world_space":[53.6318359375,-120.864948441904,-169.992823943258]},"type":{"keypoint_type":"left"}},{"coordinates":{"world_space":[55.1318359375,-124.6142578125,-202.280204778157]},"type":{"keypoint_type":"left"}},{"coordinates":{"world_space":[61.1318359375,-124.6142578125,-232.314334470989]},"type":{"keypoint_type":"left"}},{"coordinates":{"world_space":[37.1318359375,-111.1142578125,6.45699658703103]},"type":{"keypoint_type":"right"}},{"coordinates":{"world_space":[37.1318359375,-111.1142578125,-19.0720136518768]},"type":{"keypoint_type":"right"}},{"coordinates":{"world_space":[31.1318359375,-111.1142578125,-44.6010238907847]},"type":{"keypoint_type":"right"}},{"coordinates":{"world_space":[31.1318359375,-108.1142578125,-74.6351535836174]},"type":{"keypoint_type":"right"}},{"coordinates":{"world_space":[28.1318359375,-108.1142578125,-104.66928327645]},"type":{"keypoint_type":"right"}},{"coordinates":{"world_space":[26.6318359375,-109.6142578125,-137.706825938566]},"type":{"keypoint_type":"right"}},{"coordinates":{"world_space":[25.1318359375,-114.1142578125,-170.744368600682]},"type":{"keypoint_type":"right"}},{"coordinates":{"world_space":[22.1318359375,-115.6142578125,-202.280204778157]},"type":{"keypoint_type":"right"}},{"coordinates":{"world_space":[17.6318359375,-114.1142578125,-232.314334470989]},"type":{"keypoint_type":"right"}}]