[{"coordinates":{"world_space":[-28.6419852634298,-122.9550825,-84.9414790996783]},"type":{"spine_level":"T9","keypoint_type":"body"}},{"coordinates":{"world_space":[-25.6337208006198,-118.4550825,-110.414147909968]},"type":{"spine_level":"T10","keypoint_type":"body"}},{"coordinates":{"world_space":[-21.121324106405,-113.9550825,-137.385209003215]},"type":{"spine_level":"T11","keypoint_type":"body"}},{"coordinates":{"world_space":[-15.1047951807851,-118.4550825,-167.353054662379]},"type":{"spine_level":"T12","keypoint_type":"body"}},{"coordinates":{"world_space":[-13.6006629493802,-130.4550825,-194.324115755627]},"type":{"spine_level":"L1","keypoint_type":"body"}},{"coordinates":{"world_space":[-10.5923984865703,-143.9550825,-227.288745980707]},"type":{"spine_level":"L2","keypoint_type":"body"}},{"coordinates":{"world_space":[-12.0965307179752,-155.9550825,-263.250160771704]},"type":{"spine_level":"L3","keypoint_type":"body"}},{"coordinates":{"world_space":[-14.3527457661781,-159.705099155213,-298.46236278386]},"type":{"spine_level":"L4","keypoint_type":"body"}},{"coordinates":{"world_space":[-19.617191875,-149.9550825,-335.172990353698]},"type":{"spine_level":"L5","keypoint_type":"body"}},{"coordinates":{"world_space":[-13.6006629493802,-100.4550825,-68.4591639871381]},"type":{"keypoint_type":"left"}},{"coordinates":{"world_space":[-10.5923984865703,-91.4550825,-96.9286173633439]},"type":{"keypoint_type":"left"}},{"coordinates":{"world_space":[-7.58413402376033,-85.4550825,-129.893247588424]},"type":{"keypoint_type":"left"}},{"coordinates":{"world_space":[-4.57586956095042,-86.9550825,-164.356270096463]},"type":{"keypoint_type":"left"}},{"coordinates":{"world_space":[-3.07173732954546,-95.9550825,-198.819292604501]},"type":{"keypoint_type":"left"}},{"coordinates":{"world_space":[-1.5676050981405,-110.9550825,-230.285530546624]},"type":{"keypoint_type":"left"}},{"coordinates":{"world_space":[-0.0634728667355375,-122.9550825,-261.751768488746]},"type":{"keypoint_type":"left"}},{"coordinates":{"world_space":[-1.5676050981405,-128.9550825,-293.218006430868]},"type":{"keypoint_type":"left"}},{"coordinates":{"world_space":[5.9530560588843,-124.4550825,-324.68424437299]},"type":{"keypoint_type":"left"}},{"coordinates":{"world_space":[-39.1709108832645,-100.4550825,-71.4559485530545]},"type":{"keypoint_type":"right"}},{"coordinates":{"world_space":[-37.6667786518595,-94.4550825,-99.9254019292603]},"type":{"keypoint_type":"right"}},{"coordinates":{"world_space":[-37.6667786518595,-88.4550825,-129.893247588424]},"type":{"keypoint_type":"right"}},{"coordinates":{"world_space":[-37.6667786518595,-92.9550825,-164.356270096463]},"type":{"keypoint_type":"right"}},{"coordinates":{"world_space":[-34.6585141890496,-100.4550825,-195.822508038585]},"type":{"keypoint_type":"right"}},{"coordinates":{"world_space":[-33.1543819576446,-115.4550825,-230.285530546624]},"type":{"keypoint_type":"right"}},{"coordinates":{"world_space":[-34.6585141890496,-127.4550825,-260.253376205788]},"type":{"keypoint_type":"right"}},{"coordinates":{"world_space":[-36.1626464204545,-134.9550825,-291.71961414791]},"type":{"keypoint_type":"right"}},{"coordinates":{"world_space":[-49.6998365030992,-136.4550825,-321.687459807074]},"type":{"keypoint_type":"right"}}]