[{"coordinates":{"world_space":[-31.3478150406504,49.578125,19.9748611560303]},"type":{"spine_level":"T10","keypoint_type":"body"}},{"coordinates":{"world_space":[-31.3478150406504,54.078125,-6.99311037421886]},"type":{"spine_level":"T11","keypoint_type":"body"}},{"coordinates":{"world_space":[-29.84375,58.578125,-38.4557438261761]},"type":{"spine_level":"T12","keypoint_type":"body"}},{"coordinates":{"world_space":[-29.84375,61.578125,-72.9148185592722]},"type":{"spine_level":"L1","keypoint_type":"body"}},{"coordinates":{"world_space":[-28.3396849593496,63.078125,-108.872113932938]},"type":{"spine_level":"L2","keypoint_type":"body"}},{"coordinates":{"world_space":[-28.3396849593496,63.078125,-146.327629947173]},"type":{"spine_level":"L3","keypoint_type":"body"}},{"coordinates":{"world_space":[-29.84375,61.578125,-179.288484039699]},"type":{"spine_level":"L4","keypoint_type":"body"}},{"coordinates":{"world_space":[-31.3478150406504,63.078125,-212.249338132226]},"type":{"spine_level":"L5","keypoint_type":"body"}},{"coordinates":{"world_space":[-16.3071646341463,73.578125,28.9641849994466]},"type":{"keypoint_type":"left"}},{"coordinates":{"world_space":[-14.8030995934959,76.578125,1.99621346919751]},"type":{"keypoint_type":"left"}},{"coordinates":{"world_space":[-13.2990345528455,82.578125,-29.4664199827598]},"type":{"keypoint_type":"left"}},{"coordinates":{"world_space":[-13.2990345528455,88.578125,-62.4272740752865]},"type":{"keypoint_type":"left"}},{"coordinates":{"world_space":[-11.7949695121951,91.578125,-98.384569448952]},"type":{"keypoint_type":"left"}},{"coordinates":{"world_space":[-8.78683943089431,90.078125,-137.338306103756]},"type":{"keypoint_type":"left"}},{"coordinates":{"world_space":[-8.78683943089431,88.578125,-171.797380836852]},"type":{"keypoint_type":"left"}},{"coordinates":{"world_space":[-4.27464430894309,85.578125,-204.758234929379]},"type":{"keypoint_type":"left"}},{"coordinates":{"world_space":[-40.3722052845528,72.078125,28.9641849994466]},"type":{"keypoint_type":"right"}},{"coordinates":{"world_space":[-43.3803353658537,76.578125,3.49443410976691]},"type":{"keypoint_type":"right"}},{"coordinates":{"world_space":[-43.3803353658537,83.328535740777,-28.7177199160151]},"type":{"keypoint_type":"right"}},{"coordinates":{"world_space":[-44.8844004065041,88.578125,-63.9254947158559]},"type":{"keypoint_type":"right"}},{"coordinates":{"world_space":[-44.8844004065041,90.078125,-99.8827900895214]},"type":{"keypoint_type":"right"}},{"coordinates":{"world_space":[-44.8844004065041,90.078125,-138.836526744326]},"type":{"keypoint_type":"right"}},{"coordinates":{"world_space":[-49.3965955284553,88.578125,-171.797380836852]},"type":{"keypoint_type":"right"}},{"coordinates":{"world_space":[-55.4128556910569,85.578125,-201.76179364824]},"type":{"keypoint_type":"right"}}]