[{"coordinates":{"world_space":[6.953125,177.72886954698,-352.949982]},"type":{"spine_level":"T9","keypoint_type":"body"}},{"coordinates":{"world_space":[5.453125,170.21209102349,-373.949982]},"type":{"spine_level":"T10","keypoint_type":"body"}},{"coordinates":{"world_space":[3.953125,161.191956795302,-397.949982]},"type":{"spine_level":"T11","keypoint_type":"body"}},{"coordinates":{"world_space":[0.953125,153.675178271812,-424.949982]},"type":{"spine_level":"T12","keypoint_type":"body"}},{"coordinates":{"world_space":[0.953125,146.158399748322,-451.949982]},"type":{"spine_level":"L1","keypoint_type":"body"}},{"coordinates":{"world_space":[0.953125,135.634909815436,-481.949982]},"type":{"spine_level":"L2","keypoint_type":"body"}},{"coordinates":{"world_space":[2.453125,126.614775587248,-513.449982]},"type":{"spine_level":"L3","keypoint_type":"body"}},{"coordinates":{"world_space":[3.953125,122.104708473154,-547.949982]},"type":{"spine_level":"L4","keypoint_type":"body"}},{"coordinates":{"world_space":[5.453125,128.118131291946,-583.949982]},"type":{"spine_level":"L5","keypoint_type":"body"}},{"coordinates":{"world_space":[17.453125,197.272493708054,-349.949982]},"type":{"keypoint_type":"left"}},{"coordinates":{"world_space":[18.953125,189.755715184564,-372.449982]},"type":{"keypoint_type":"left"}},{"coordinates":{"world_space":[18.953125,182.238936661074,-397.949982]},"type":{"keypoint_type":"left"}},{"coordinates":{"world_space":[18.953125,173.218802432886,-424.949982]},"type":{"keypoint_type":"left"}},{"coordinates":{"world_space":[17.453125,167.205379614094,-451.949982]},"type":{"keypoint_type":"left"}},{"coordinates":{"world_space":[15.953125,156.681889681208,-481.949982]},"type":{"keypoint_type":"left"}},{"coordinates":{"world_space":[17.453125,146.158399748322,-510.449982]},"type":{"keypoint_type":"left"}},{"coordinates":{"world_space":[21.953125,141.648332634228,-540.449982]},"type":{"keypoint_type":"left"}},{"coordinates":{"world_space":[26.453125,143.151688338926,-570.449982]},"type":{"keypoint_type":"left"}},{"coordinates":{"world_space":[-5.046875,195.769138003356,-351.449982]},"type":{"keypoint_type":"right"}},{"coordinates":{"world_space":[-5.046875,189.755715184564,-372.449982]},"type":{"keypoint_type":"right"}},{"coordinates":{"world_space":[-5.046875,182.238936661074,-397.949982]},"type":{"keypoint_type":"right"}},{"coordinates":{"world_space":[-9.546875,176.225513842282,-426.449982]},"type":{"keypoint_type":"right"}},{"coordinates":{"world_space":[-11.046875,168.708735318792,-451.949982]},"type":{"keypoint_type":"right"}},{"coordinates":{"world_space":[-11.046875,158.185245385906,-481.949982]},"type":{"keypoint_type":"right"}},{"coordinates":{"world_space":[-11.046875,149.165111157718,-511.949982]},"type":{"keypoint_type":"right"}},{"coordinates":{"world_space":[-14.046875,143.151688338926,-541.949982]},"type":{"keypoint_type":"right"}},{"coordinates":{"world_space":[-15.546875,144.655044043624,-573.449982]},"type":{"keypoint_type":"right"}}]