[{"coordinates":{"world_space":[-6.63867625,264.313432211257,-52.1636636636636]},"type":{"spine_level":"T9","keypoint_type":"body"}},{"coordinates":{"world_space":[-6.63867625,259.804660281433,-77.6381381381381]},"type":{"spine_level":"T10","keypoint_type":"body"}},{"coordinates":{"world_space":[-6.63867625,253.792964375,-106.10960960961]},"type":{"spine_level":"T11","keypoint_type":"body"}},{"coordinates":{"world_space":[-6.63867625,246.278344491959,-137.578078078078]},"type":{"spine_level":"T12","keypoint_type":"body"}},{"coordinates":{"world_space":[-8.13867625,235.757876655702,-172.043543543544]},"type":{"spine_level":"L1","keypoint_type":"body"}},{"coordinates":{"world_space":[-6.63867625,223.734484842836,-209.506006006006]},"type":{"spine_level":"L2","keypoint_type":"body"}},{"coordinates":{"world_space":[-8.13867625,211.711093029971,-248.466966966967]},"type":{"spine_level":"L3","keypoint_type":"body"}},{"coordinates":{"world_space":[-6.63867625,202.693549170322,-290.424924924925]},"type":{"spine_level":"L4","keypoint_type":"body"}},{"coordinates":{"world_space":[-8.13867625,201.190625193713,-329.385885885886]},"type":{"spine_level":"L5","keypoint_type":"body"}},{"coordinates":{"world_space":[11.36132375,292.868987766813,-47.6681681681682]},"type":{"keypoint_type":"left"}},{"coordinates":{"world_space":[11.36132375,288.360215836988,-76.1396396396396]},"type":{"keypoint_type":"left"}},{"coordinates":{"world_space":[12.86132375,280.845595953947,-107.608108108108]},"type":{"keypoint_type":"left"}},{"coordinates":{"world_space":[12.86132375,273.330976070906,-139.076576576577]},"type":{"keypoint_type":"left"}},{"coordinates":{"world_space":[12.86132375,264.313432211257,-173.542042042042]},"type":{"keypoint_type":"left"}},{"coordinates":{"world_space":[11.36132375,252.290040398392,-209.506006006006]},"type":{"keypoint_type":"left"}},{"coordinates":{"world_space":[11.36132375,240.266648585526,-246.968468468468]},"type":{"keypoint_type":"left"}},{"coordinates":{"world_space":[12.86132375,231.249104725877,-287.427927927928]},"type":{"keypoint_type":"left"}},{"coordinates":{"world_space":[14.36132375,226.740332796053,-324.89039039039]},"type":{"keypoint_type":"left"}},{"coordinates":{"world_space":[-15.63867625,294.371911743421,-47.6681681681682]},"type":{"keypoint_type":"right"}},{"coordinates":{"world_space":[-17.13867625,288.360215836988,-74.6411411411411]},"type":{"keypoint_type":"right"}},{"coordinates":{"world_space":[-18.63867625,282.348519930556,-106.10960960961]},"type":{"keypoint_type":"right"}},{"coordinates":{"world_space":[-21.63867625,274.833900047515,-137.578078078078]},"type":{"keypoint_type":"right"}},{"coordinates":{"world_space":[-23.13867625,265.816356187865,-172.043543543544]},"type":{"keypoint_type":"right"}},{"coordinates":{"world_space":[-23.13867625,253.792964375,-209.506006006006]},"type":{"keypoint_type":"right"}},{"coordinates":{"world_space":[-24.63867625,240.266648585526,-246.968468468468]},"type":{"keypoint_type":"right"}},{"coordinates":{"world_space":[-26.13867625,231.249104725877,-287.427927927928]},"type":{"keypoint_type":"right"}},{"coordinates":{"world_space":[-32.13867625,223.734484842836,-321.893393393393]},"type":{"keypoint_type":"right"}}]