[{"coordinates":{"world_space":[10.5708410743802,57.762348,-30.3128586231348]},"type":{"spine_level":"T7","keypoint_type":"body"}},{"coordinates":{"world_space":[6.08323776859505,51.762348,-54.3355215126533]},"type":{"spine_level":"T8","keypoint_type":"body"}},{"coordinates":{"world_space":[3.09150223140497,47.262348,-81.3610172633615]},"type":{"spine_level":"T9","keypoint_type":"body"}},{"coordinates":{"world_space":[3.09150223140497,41.262348,-108.38651301407]},"type":{"spine_level":"T10","keypoint_type":"body"}},{"coordinates":{"world_space":[0.0997666942148836,33.762348,-138.414841625968]},"type":{"spine_level":"T11","keypoint_type":"body"}},{"coordinates":{"world_space":[0.0997666942148836,23.262348,-166.941753807271]},"type":{"spine_level":"T12","keypoint_type":"body"}},{"coordinates":{"world_space":[0.0997666942148836,11.262348,-202.975748141548]},"type":{"spine_level":"L1","keypoint_type":"body"}},{"coordinates":{"world_space":[1.59563446280992,-0.737651999999976,-240.511158906421]},"type":{"spine_level":"L2","keypoint_type":"body"}},{"coordinates":{"world_space":[3.09150223140497,-8.23765199999998,-281.049402532483]},"type":{"spine_level":"L3","keypoint_type":"body"}},{"coordinates":{"world_space":[3.09150223140497,-8.23765199999998,-321.587646158546]},"type":{"spine_level":"L4","keypoint_type":"body"}},{"coordinates":{"world_space":[6.08323776859505,12.762348,-354.618807631633]},"type":{"spine_level":"L5","keypoint_type":"body"}},{"coordinates":{"world_space":[24.0336509917355,80.262348,-24.3071929007552]},"type":{"keypoint_type":"left"}},{"coordinates":{"world_space":[24.0336509917355,77.262348,-48.3298557902737]},"type":{"keypoint_type":"left"}},{"coordinates":{"world_space":[24.0336509917355,74.262348,-78.3581844021717]},"type":{"keypoint_type":"left"}},{"coordinates":{"world_space":[22.5377832231405,69.762348,-108.38651301407]},"type":{"keypoint_type":"left"}},{"coordinates":{"world_space":[21.0419154545455,63.762348,-139.916258056563]},"type":{"keypoint_type":"left"}},{"coordinates":{"world_space":[19.5460476859504,53.262348,-171.446003099056]},"type":{"keypoint_type":"left"}},{"coordinates":{"world_space":[19.5460476859504,39.762348,-205.978581002738]},"type":{"keypoint_type":"left"}},{"coordinates":{"world_space":[19.5460476859504,27.762348,-239.009742475826]},"type":{"keypoint_type":"left"}},{"coordinates":{"world_space":[21.0419154545455,20.262348,-275.043736810104]},"type":{"keypoint_type":"left"}},{"coordinates":{"world_space":[24.0336509917355,20.262348,-309.576314713786]},"type":{"keypoint_type":"left"}},{"coordinates":{"world_space":[33.0088576033058,30.762348,-336.601810464495]},"type":{"keypoint_type":"left"}},{"coordinates":{"world_space":[-1.39610107438016,77.262348,-22.8057764701603]},"type":{"keypoint_type":"right"}},{"coordinates":{"world_space":[-2.8919688429752,77.262348,-48.3298557902737]},"type":{"keypoint_type":"right"}},{"coordinates":{"world_space":[-4.38783661157024,74.262348,-76.8567679715768]},"type":{"keypoint_type":"right"}},{"coordinates":{"world_space":[-5.88370438016528,69.762348,-105.38368015288]},"type":{"keypoint_type":"right"}},{"coordinates":{"world_space":[-10.3713076859504,63.762348,-136.913425195373]},"type":{"keypoint_type":"right"}},{"coordinates":{"world_space":[-14.8589109917355,56.262348,-171.446003099056]},"type":{"keypoint_type":"right"}},{"coordinates":{"world_space":[-16.3547787603306,41.262348,-204.477164572143]},"type":{"keypoint_type":"right"}},{"coordinates":{"world_space":[-16.3547787603306,30.762348,-239.009742475826]},"type":{"keypoint_type":"right"}},{"coordinates":{"world_space":[-17.8506465289256,23.262348,-275.043736810104]},"type":{"keypoint_type":"right"}},{"coordinates":{"world_space":[-19.3465142975207,20.262348,-311.077731144381]},"type":{"keypoint_type":"right"}},{"coordinates":{"world_space":[-22.3382498347107,33.762348,-338.10322689509]},"type":{"keypoint_type":"right"}}]