[{"coordinates":{"world_space":[-15.16294,-104.2187525,-106.553846153846]},"type":{"spine_level":"T11","keypoint_type":"body"}},{"coordinates":{"world_space":[-10.67494,-113.2187525,-138.011336032389]},"type":{"spine_level":"T12","keypoint_type":"body"}},{"coordinates":{"world_space":[-3.19493999999999,-120.7187525,-173.962753036437]},"type":{"spine_level":"L1","keypoint_type":"body"}},{"coordinates":{"world_space":[4.28506000000001,-128.2187525,-211.412145748988]},"type":{"spine_level":"L2","keypoint_type":"body"}},{"coordinates":{"world_space":[8.77306000000001,-132.7187525,-251.857489878542]},"type":{"spine_level":"L3","keypoint_type":"body"}},{"coordinates":{"world_space":[10.26906,-128.2187525,-293.800809716599]},"type":{"spine_level":"L4","keypoint_type":"body"}},{"coordinates":{"world_space":[-0.202939999999994,-78.7187525,-102.05991902834]},"type":{"keypoint_type":"left"}},{"coordinates":{"world_space":[7.27706000000001,-84.7187525,-133.517408906882]},"type":{"keypoint_type":"left"}},{"coordinates":{"world_space":[11.76506,-92.2187525,-167.970850202429]},"type":{"keypoint_type":"left"}},{"coordinates":{"world_space":[19.24506,-101.2187525,-203.922267206478]},"type":{"keypoint_type":"left"}},{"coordinates":{"world_space":[28.22106,-105.7187525,-244.367611336032]},"type":{"keypoint_type":"left"}},{"coordinates":{"world_space":[29.71706,-104.2187525,-280.319028340081]},"type":{"keypoint_type":"left"}},{"coordinates":{"world_space":[-30.12294,-78.7187525,-106.553846153846]},"type":{"keypoint_type":"right"}},{"coordinates":{"world_space":[-25.63494,-84.7187525,-139.509311740891]},"type":{"keypoint_type":"right"}},{"coordinates":{"world_space":[-19.65094,-92.2187525,-173.962753036437]},"type":{"keypoint_type":"right"}},{"coordinates":{"world_space":[-13.66694,-101.2187525,-209.914170040486]},"type":{"keypoint_type":"right"}},{"coordinates":{"world_space":[-10.67494,-107.2187525,-245.865587044534]},"type":{"keypoint_type":"right"}},{"coordinates":{"world_space":[-11.4234154154778,-105.7187525,-281.068492237672]},"type":{"keypoint_type":"right"}}]