[{"coordinates":{"world_space":[-9.90625,-89.7139163669065,-61.464150943396]},"type":{"spine_level":"T10","keypoint_type":"body"}},{"coordinates":{"world_space":[-9.90625,-95.6995278776978,-85.4339622641508]},"type":{"spine_level":"T11","keypoint_type":"body"}},{"coordinates":{"world_space":[-9.90625,-101.685139388489,-113.898113207547]},"type":{"spine_level":"T12","keypoint_type":"body"}},{"coordinates":{"world_space":[-9.90625,-107.670750899281,-145.358490566038]},"type":{"spine_level":"L1","keypoint_type":"body"}},{"coordinates":{"world_space":[-9.90625,-113.656362410072,-178.316981132075]},"type":{"spine_level":"L2","keypoint_type":"body"}},{"coordinates":{"world_space":[-9.90625,-121.138376798561,-212.77358490566]},"type":{"spine_level":"L3","keypoint_type":"body"}},{"coordinates":{"world_space":[-9.90625,-124.131182553957,-248.728301886792]},"type":{"spine_level":"L4","keypoint_type":"body"}},{"coordinates":{"world_space":[-11.40625,-124.131182553957,-283.184905660377]},"type":{"spine_level":"L5","keypoint_type":"body"}},{"coordinates":{"world_space":[2.09375,-70.2606789568345,-56.9698113207545]},"type":{"keypoint_type":"left"}},{"coordinates":{"world_space":[2.09375,-73.2534847122302,-80.9396226415093]},"type":{"keypoint_type":"left"}},{"coordinates":{"world_space":[2.09375,-77.7426933453237,-109.403773584905]},"type":{"keypoint_type":"left"}},{"coordinates":{"world_space":[2.09375,-82.2319019784173,-140.864150943396]},"type":{"keypoint_type":"left"}},{"coordinates":{"world_space":[0.59375,-89.7139163669065,-173.822641509434]},"type":{"keypoint_type":"left"}},{"coordinates":{"world_space":[0.59375,-95.6995278776978,-208.279245283019]},"type":{"keypoint_type":"left"}},{"coordinates":{"world_space":[0.59375,-100.188736510791,-244.233962264151]},"type":{"keypoint_type":"left"}},{"coordinates":{"world_space":[5.09375,-101.685139388489,-274.196226415094]},"type":{"keypoint_type":"left"}},{"coordinates":{"world_space":[-21.90625,-73.2534847122302,-55.4716981132074]},"type":{"keypoint_type":"right"}},{"coordinates":{"world_space":[-21.90625,-73.2534847122302,-79.4415094339621]},"type":{"keypoint_type":"right"}},{"coordinates":{"world_space":[-24.90625,-79.2390962230216,-109.403773584905]},"type":{"keypoint_type":"right"}},{"coordinates":{"world_space":[-24.90625,-85.2247077338129,-140.864150943396]},"type":{"keypoint_type":"right"}},{"coordinates":{"world_space":[-26.40625,-92.7067221223022,-173.822641509434]},"type":{"keypoint_type":"right"}},{"coordinates":{"world_space":[-27.90625,-101.685139388489,-206.781132075472]},"type":{"keypoint_type":"right"}},{"coordinates":{"world_space":[-27.90625,-106.174348021583,-242.735849056604]},"type":{"keypoint_type":"right"}},{"coordinates":{"world_space":[-33.90625,-107.670750899281,-274.196226415094]},"type":{"keypoint_type":"right"}}]