[{"coordinates":{"world_space":[-1.17893437499999,259.494786704193,-29.0666666666664]},"type":{"spine_level":"T8","keypoint_type":"body"}},{"coordinates":{"world_space":[-2.68293437499999,250.513420244565,-48.5447811447809]},"type":{"spine_level":"T9","keypoint_type":"body"}},{"coordinates":{"world_space":[-4.18693437499999,243.028948194876,-72.5178451178449]},"type":{"spine_level":"T10","keypoint_type":"body"}},{"coordinates":{"world_space":[-7.19493437499999,237.041370555124,-97.9892255892253]},"type":{"spine_level":"T11","keypoint_type":"body"}},{"coordinates":{"world_space":[-8.69893437499999,229.556898505435,-124.958922558922]},"type":{"spine_level":"T12","keypoint_type":"body"}},{"coordinates":{"world_space":[-8.69893437499999,220.575532045807,-154.925252525252]},"type":{"spine_level":"L1","keypoint_type":"body"}},{"coordinates":{"world_space":[-13.210934375,208.600376766304,-186.389898989899]},"type":{"spine_level":"L2","keypoint_type":"body"}},{"coordinates":{"world_space":[-19.226934375,199.619010306677,-217.854545454545]},"type":{"spine_level":"L3","keypoint_type":"body"}},{"coordinates":{"world_space":[-20.730934375,195.128327076863,-255.312457912458]},"type":{"spine_level":"L4","keypoint_type":"body"}},{"coordinates":{"world_space":[-22.234934375,195.128327076863,-291.272053872054]},"type":{"spine_level":"L5","keypoint_type":"body"}},{"coordinates":{"world_space":[12.357065625,280.451308443323,-27.5683501683499]},"type":{"keypoint_type":"left"}},{"coordinates":{"world_space":[10.853065625,272.966836393634,-48.5447811447809]},"type":{"keypoint_type":"left"}},{"coordinates":{"world_space":[10.853065625,268.47615316382,-72.5178451178449]},"type":{"keypoint_type":"left"}},{"coordinates":{"world_space":[12.357065625,262.488575524068,-99.4875420875418]},"type":{"keypoint_type":"left"}},{"coordinates":{"world_space":[10.853065625,255.004103474379,-129.453872053872]},"type":{"keypoint_type":"left"}},{"coordinates":{"world_space":[7.84506562500001,246.022737014752,-159.420202020202]},"type":{"keypoint_type":"left"}},{"coordinates":{"world_space":[4.83706562500001,235.544476145186,-189.386531986532]},"type":{"keypoint_type":"left"}},{"coordinates":{"world_space":[1.82906562500001,225.066215275621,-219.352861952862]},"type":{"keypoint_type":"left"}},{"coordinates":{"world_space":[1.82906562500001,220.575532045807,-252.315824915825]},"type":{"keypoint_type":"left"}},{"coordinates":{"world_space":[4.83706562500001,219.07863763587,-280.783838383838]},"type":{"keypoint_type":"left"}},{"coordinates":{"world_space":[-10.202934375,278.954414033385,-26.0700336700334]},"type":{"keypoint_type":"right"}},{"coordinates":{"world_space":[-13.210934375,272.966836393634,-47.0464646464644]},"type":{"keypoint_type":"right"}},{"coordinates":{"world_space":[-14.714934375,268.47615316382,-71.0195286195284]},"type":{"keypoint_type":"right"}},{"coordinates":{"world_space":[-17.722934375,263.236964434341,-98.7383254883059]},"type":{"keypoint_type":"right"}},{"coordinates":{"world_space":[-22.234934375,256.500997884317,-127.955555555555]},"type":{"keypoint_type":"right"}},{"coordinates":{"world_space":[-22.234934375,247.519631424689,-154.925252525252]},"type":{"keypoint_type":"right"}},{"coordinates":{"world_space":[-26.746934375,238.538264965062,-184.891582491582]},"type":{"keypoint_type":"right"}},{"coordinates":{"world_space":[-34.266934375,229.556898505435,-216.356228956229]},"type":{"keypoint_type":"right"}},{"coordinates":{"world_space":[-40.282934375,222.072426455745,-249.319191919192]},"type":{"keypoint_type":"right"}},{"coordinates":{"world_space":[-47.802934375,220.575532045807,-280.783838383838]},"type":{"keypoint_type":"right"}}]