[{"coordinates":{"world_space":[-1.18894387804877,45.0383203598726,-69.315002]},"type":{"spine_level":"T9","keypoint_type":"body"}},{"coordinates":{"world_space":[-2.69300891869918,39.0510592133758,-97.815002]},"type":{"spine_level":"T10","keypoint_type":"body"}},{"coordinates":{"world_space":[-5.70113899999999,34.5606133535032,-126.315002]},"type":{"spine_level":"T11","keypoint_type":"body"}},{"coordinates":{"world_space":[-5.70113899999999,27.0765369203822,-159.315002]},"type":{"spine_level":"T12","keypoint_type":"body"}},{"coordinates":{"world_space":[-5.70113899999999,19.5924604872612,-193.815002]},"type":{"spine_level":"L1","keypoint_type":"body"}},{"coordinates":{"world_space":[-5.70113899999999,10.6115687675159,-231.315002]},"type":{"spine_level":"L2","keypoint_type":"body"}},{"coordinates":{"world_space":[-7.2052040406504,1.63067704777072,-267.315002]},"type":{"spine_level":"L3","keypoint_type":"body"}},{"coordinates":{"world_space":[-8.7092690813008,-7.35021467197451,-304.815002]},"type":{"spine_level":"L4","keypoint_type":"body"}},{"coordinates":{"world_space":[-11.7173991626016,-4.3565840987261,-345.315002]},"type":{"spine_level":"L5","keypoint_type":"body"}},{"coordinates":{"world_space":[15.3557715691057,68.9873649458599,-66.315002]},"type":{"keypoint_type":"left"}},{"coordinates":{"world_space":[12.3476414878049,64.4969190859873,-93.315002]},"type":{"keypoint_type":"left"}},{"coordinates":{"world_space":[11.5953971995231,58.5096579394905,-124.064790804389]},"type":{"keypoint_type":"left"}},{"coordinates":{"world_space":[13.8517065284553,52.5223967929936,-159.315002]},"type":{"keypoint_type":"left"}},{"coordinates":{"world_space":[13.8517065284553,46.5351356464968,-193.815002]},"type":{"keypoint_type":"left"}},{"coordinates":{"world_space":[12.3476414878049,37.5542439267516,-229.815002]},"type":{"keypoint_type":"left"}},{"coordinates":{"world_space":[12.3476414878049,30.0701674936306,-268.815002]},"type":{"keypoint_type":"left"}},{"coordinates":{"world_space":[10.8435764471545,21.0892757738854,-303.315002]},"type":{"keypoint_type":"left"}},{"coordinates":{"world_space":[15.3557715691057,16.5988299140128,-336.315002]},"type":{"keypoint_type":"left"}},{"coordinates":{"world_space":[-10.2133341219512,68.9873649458599,-63.315002]},"type":{"keypoint_type":"right"}},{"coordinates":{"world_space":[-13.221464203252,64.4969190859873,-91.815002]},"type":{"keypoint_type":"right"}},{"coordinates":{"world_space":[-17.7336593252032,60.0064732261147,-123.315002]},"type":{"keypoint_type":"right"}},{"coordinates":{"world_space":[-20.7417894065041,54.0192120796178,-157.815002]},"type":{"keypoint_type":"right"}},{"coordinates":{"world_space":[-20.7417894065041,48.031950933121,-193.815002]},"type":{"keypoint_type":"right"}},{"coordinates":{"world_space":[-22.2458544471545,39.0510592133758,-228.315002]},"type":{"keypoint_type":"right"}},{"coordinates":{"world_space":[-25.2539845284553,28.5733522070064,-265.815002]},"type":{"keypoint_type":"right"}},{"coordinates":{"world_space":[-26.7580495691057,19.5924604872612,-300.315002]},"type":{"keypoint_type":"right"}},{"coordinates":{"world_space":[-34.2783747723577,16.5988299140128,-333.315002]},"type":{"keypoint_type":"right"}}]