[{"coordinates":{"world_space":[-11.8496900826446,241.872635135135,-55.7499999999998]},"type":{"spine_level":"T10","keypoint_type":"body"}},{"coordinates":{"world_space":[-11.8496900826446,223.905067567568,-75.2499999999998]},"type":{"spine_level":"T11","keypoint_type":"body"}},{"coordinates":{"world_space":[-11.8496900826446,208.932094594595,-99.2499999999998]},"type":{"spine_level":"T12","keypoint_type":"body"}},{"coordinates":{"world_space":[-5.83316115702479,192.461824324324,-124.75]},"type":{"spine_level":"L1","keypoint_type":"body"}},{"coordinates":{"world_space":[-1.32076446280992,174.494256756757,-153.25]},"type":{"spine_level":"L2","keypoint_type":"body"}},{"coordinates":{"world_space":[3.19163223140496,156.526689189189,-184.75]},"type":{"spine_level":"L3","keypoint_type":"body"}},{"coordinates":{"world_space":[7.70402892561984,147.542905405405,-222.25]},"type":{"spine_level":"L4","keypoint_type":"body"}},{"coordinates":{"world_space":[10.7122933884298,150.5375,-261.25]},"type":{"spine_level":"L5","keypoint_type":"body"}},{"coordinates":{"world_space":[0.183367768595041,261.3375,-57.2499999999998]},"type":{"keypoint_type":"left"}},{"coordinates":{"world_space":[4.69576446280992,247.861824324324,-81.2499999999998]},"type":{"keypoint_type":"left"}},{"coordinates":{"world_space":[6.19989669421488,232.888851351351,-106.75]},"type":{"keypoint_type":"left"}},{"coordinates":{"world_space":[9.20816115702479,216.418581081081,-133.75]},"type":{"keypoint_type":"left"}},{"coordinates":{"world_space":[10.7122933884298,199.948310810811,-159.25]},"type":{"keypoint_type":"left"}},{"coordinates":{"world_space":[16.7288223140496,184.975337837838,-187.75]},"type":{"keypoint_type":"left"}},{"coordinates":{"world_space":[22.7453512396694,174.494256756757,-219.25]},"type":{"keypoint_type":"left"}},{"coordinates":{"world_space":[30.2660123966942,174.494256756757,-249.25]},"type":{"keypoint_type":"left"}},{"coordinates":{"world_space":[-23.8827479338843,261.3375,-58.7499999999998]},"type":{"keypoint_type":"right"}},{"coordinates":{"world_space":[-23.8827479338843,247.861824324324,-82.7499999999998]},"type":{"keypoint_type":"right"}},{"coordinates":{"world_space":[-23.8827479338843,232.888851351351,-108.25]},"type":{"keypoint_type":"right"}},{"coordinates":{"world_space":[-19.3703512396694,216.418581081081,-135.25]},"type":{"keypoint_type":"right"}},{"coordinates":{"world_space":[-16.3620867768595,198.451013513514,-162.25]},"type":{"keypoint_type":"right"}},{"coordinates":{"world_space":[-14.8579545454545,180.483445945946,-192.25]},"type":{"keypoint_type":"right"}},{"coordinates":{"world_space":[-11.8496900826446,168.505067567568,-222.25]},"type":{"keypoint_type":"right"}},{"coordinates":{"world_space":[-13.3538223140496,168.505067567568,-252.25]},"type":{"keypoint_type":"right"}}]