[{"coordinates":{"world_space":[23.218445625,-115.307222575163,-473.843378226415]},"type":{"spine_level":"T10","keypoint_type":"body"}},{"coordinates":{"world_space":[23.218445625,-118.300686627451,-497.87356690566]},"type":{"spine_level":"T11","keypoint_type":"body"}},{"coordinates":{"world_space":[24.718445625,-119.797418653595,-527.911302754717]},"type":{"spine_level":"T12","keypoint_type":"body"}},{"coordinates":{"world_space":[24.718445625,-121.294150679739,-560.952812188679]},"type":{"spine_level":"L1","keypoint_type":"body"}},{"coordinates":{"world_space":[23.218445625,-118.300686627451,-595.496208415094]},"type":{"spine_level":"L2","keypoint_type":"body"}},{"coordinates":{"world_space":[18.718445625,-109.320294470588,-631.541491433962]},"type":{"spine_level":"L3","keypoint_type":"body"}},{"coordinates":{"world_space":[17.218445625,-92.8562421830065,-666.084887660377]},"type":{"spine_level":"L4","keypoint_type":"body"}},{"coordinates":{"world_space":[17.218445625,-74.895457869281,-696.122623509434]},"type":{"spine_level":"L5","keypoint_type":"body"}},{"coordinates":{"world_space":[35.218445625,-95.8497062352941,-464.832057471698]},"type":{"keypoint_type":"left"}},{"coordinates":{"world_space":[36.718445625,-97.3464382614379,-491.866019735849]},"type":{"keypoint_type":"left"}},{"coordinates":{"world_space":[38.218445625,-97.3464382614379,-523.405642377359]},"type":{"keypoint_type":"left"}},{"coordinates":{"world_space":[38.218445625,-98.8431702875817,-554.945265018868]},"type":{"keypoint_type":"left"}},{"coordinates":{"world_space":[36.718445625,-97.3464382614379,-587.98677445283]},"type":{"keypoint_type":"left"}},{"coordinates":{"world_space":[35.218445625,-91.3595101568628,-619.52639709434]},"type":{"keypoint_type":"left"}},{"coordinates":{"world_space":[36.718445625,-77.8889219215686,-651.066019735849]},"type":{"keypoint_type":"left"}},{"coordinates":{"world_space":[42.718445625,-61.4248696339869,-678.099982]},"type":{"keypoint_type":"left"}},{"coordinates":{"world_space":[11.218445625,-95.8497062352941,-466.333944264151]},"type":{"keypoint_type":"right"}},{"coordinates":{"world_space":[11.218445625,-97.3464382614379,-491.866019735849]},"type":{"keypoint_type":"right"}},{"coordinates":{"world_space":[11.218445625,-98.8431702875817,-523.405642377359]},"type":{"keypoint_type":"right"}},{"coordinates":{"world_space":[11.218445625,-100.339902313726,-553.443378226415]},"type":{"keypoint_type":"right"}},{"coordinates":{"world_space":[8.21844562499999,-98.8431702875817,-586.484887660377]},"type":{"keypoint_type":"right"}},{"coordinates":{"world_space":[3.71844562499999,-91.3595101568628,-618.024510301887]},"type":{"keypoint_type":"right"}},{"coordinates":{"world_space":[-0.781554375000013,-76.3921898954248,-649.564132943396]},"type":{"keypoint_type":"right"}},{"coordinates":{"world_space":[-5.28155437500001,-59.9281376078431,-681.103755584906]},"type":{"keypoint_type":"right"}}]