[{"coordinates":{"world_space":[-32.8214142628205,-82.03125,-388.05]},"type":{"spine_level":"T12","keypoint_type":"body"}},{"coordinates":{"world_space":[-34.317140758547,-85.03125,-418.05]},"type":{"spine_level":"L1","keypoint_type":"body"}},{"coordinates":{"world_space":[-34.317140758547,-92.53125,-449.55]},"type":{"spine_level":"L2","keypoint_type":"body"}},{"coordinates":{"world_space":[-34.317140758547,-101.53125,-482.55]},"type":{"spine_level":"L3","keypoint_type":"body"}},{"coordinates":{"world_space":[-35.8128672542735,-110.53125,-515.55]},"type":{"spine_level":"L4","keypoint_type":"body"}},{"coordinates":{"world_space":[-37.30859375,-112.03125,-551.55]},"type":{"spine_level":"L5","keypoint_type":"body"}},{"coordinates":{"world_space":[-20.8556022970085,-58.03125,-382.05]},"type":{"keypoint_type":"left"}},{"coordinates":{"world_space":[-22.351328792735,-59.53125,-415.05]},"type":{"keypoint_type":"left"}},{"coordinates":{"world_space":[-22.351328792735,-65.53125,-449.55]},"type":{"keypoint_type":"left"}},{"coordinates":{"world_space":[-22.351328792735,-74.53125,-482.55]},"type":{"keypoint_type":"left"}},{"coordinates":{"world_space":[-22.351328792735,-85.03125,-514.05]},"type":{"keypoint_type":"left"}},{"coordinates":{"world_space":[-20.8556022970085,-89.53125,-544.05]},"type":{"keypoint_type":"left"}},{"coordinates":{"world_space":[-46.282952724359,-61.03125,-380.55]},"type":{"keypoint_type":"right"}},{"coordinates":{"world_space":[-49.274405715812,-62.53125,-415.05]},"type":{"keypoint_type":"right"}},{"coordinates":{"world_space":[-50.7701322115385,-68.53125,-446.55]},"type":{"keypoint_type":"right"}},{"coordinates":{"world_space":[-52.265858707265,-79.03125,-481.05]},"type":{"keypoint_type":"right"}},{"coordinates":{"world_space":[-55.2573116987179,-88.03125,-512.55]},"type":{"keypoint_type":"right"}},{"coordinates":{"world_space":[-59.7444911858974,-92.53125,-544.05]},"type":{"keypoint_type":"right"}}]