[{"coordinates":{"world_space":[1.79135722268909,55.6464315,-67.8517408197613]},"type":{"spine_level":"T10","keypoint_type":"body"}},{"coordinates":{"world_space":[0.287155542016817,43.6464315,-90.3804764519452]},"type":{"spine_level":"T11","keypoint_type":"body"}},{"coordinates":{"world_space":[-1.21704613865545,31.6464315,-118.916874919378]},"type":{"spine_level":"T12","keypoint_type":"body"}},{"coordinates":{"world_space":[-4.22544949999999,19.6464315,-147.453273386811]},"type":{"spine_level":"L1","keypoint_type":"body"}},{"coordinates":{"world_space":[-4.22544949999999,6.14643150000001,-178.993503271869]},"type":{"spine_level":"L2","keypoint_type":"body"}},{"coordinates":{"world_space":[-5.72965118067226,-5.85356849999999,-212.035648865738]},"type":{"spine_level":"L3","keypoint_type":"body"}},{"coordinates":{"world_space":[-7.23385286134453,-13.3535685,-249.583541586045]},"type":{"spine_level":"L4","keypoint_type":"body"}},{"coordinates":{"world_space":[-10.2422562226891,-11.8535685,-285.629518597539]},"type":{"spine_level":"L5","keypoint_type":"body"}},{"coordinates":{"world_space":[16.8333740294118,78.1464315,-69.3536565285735]},"type":{"keypoint_type":"left"}},{"coordinates":{"world_space":[16.8333740294118,67.6464315,-94.886223578382]},"type":{"keypoint_type":"left"}},{"coordinates":{"world_space":[15.3291723487395,55.6464315,-124.924537754627]},"type":{"keypoint_type":"left"}},{"coordinates":{"world_space":[13.8249706680672,43.6464315,-153.46093622206]},"type":{"keypoint_type":"left"}},{"coordinates":{"world_space":[12.320768987395,30.1464315,-183.499250398305]},"type":{"keypoint_type":"left"}},{"coordinates":{"world_space":[12.320768987395,18.1464315,-215.039480283363]},"type":{"keypoint_type":"left"}},{"coordinates":{"world_space":[10.8165673067227,12.1464315,-248.081625877233]},"type":{"keypoint_type":"left"}},{"coordinates":{"world_space":[16.8333740294118,9.14643150000001,-279.62185576229]},"type":{"keypoint_type":"left"}},{"coordinates":{"world_space":[-7.23385286134453,79.6464315,-67.8517408197613]},"type":{"keypoint_type":"right"}},{"coordinates":{"world_space":[-8.7380545420168,70.6464315,-94.886223578382]},"type":{"keypoint_type":"right"}},{"coordinates":{"world_space":[-13.2506595840336,58.6464315,-123.422622045815]},"type":{"keypoint_type":"right"}},{"coordinates":{"world_space":[-16.2590629453781,46.6464315,-153.46093622206]},"type":{"keypoint_type":"right"}},{"coordinates":{"world_space":[-19.2674663067227,31.6464315,-183.499250398305]},"type":{"keypoint_type":"right"}},{"coordinates":{"world_space":[-20.7716679873949,19.6464315,-213.537564574551]},"type":{"keypoint_type":"right"}},{"coordinates":{"world_space":[-25.2842730294118,12.1464315,-245.077794459608]},"type":{"keypoint_type":"right"}},{"coordinates":{"world_space":[-32.8052814327731,10.6464315,-278.119940053478]},"type":{"keypoint_type":"right"}}]